{"_":["index.js"],"open":false,"o":false,"version":false,"v":false,"help":false,"h":false,"quiet":false,"q":false,"silent":false,"s":false,"treeDebug":false,"tree-debug":false,"kernelTracingDebug":false,"kernel-tracing-debug":false,"kernelTracing":false,"kernel-tracing":false,"collectOnly":false,"collect-only":false,"writeTicks":false,"write-ticks":false,"--":[],"workingDir":"D:\\FRANCO\\Curso programacion\\Practica\\router","argv":["index.js"],"pathToNodeBinary":"C:\\Program Files\\nodejs\\node.exe","name":"flamegraph","collectDelay":0,"title":"node index.js","pid":10144,"inlined":{"isPathSeparator node:path":[{"file":"node:path","fn":"isPathSeparator","id":"0","ix":"0","pos":"1794","caller":{"file":"node:path","fn":"normalizeString","id":"0","ix":"-1","pos":"2226","key":"normalizeString node:path"}},{"file":"node:path","fn":"isPathSeparator","id":"0","ix":"0","pos":"1794","caller":{"file":"node:path","fn":"normalizeString","id":"0","ix":"-1","pos":"2226","key":"normalizeString node:path"}},{"file":"node:path","fn":"isPathSeparator","id":"1","ix":"0","pos":"1794","caller":{"file":"node:path","fn":"resolve","id":"1","ix":"-1","pos":"4875","key":"resolve node:path"}},{"file":"node:path","fn":"isPathSeparator","id":"1","ix":"0","pos":"1794","caller":{"file":"node:path","fn":"resolve","id":"1","ix":"-1","pos":"4875","key":"resolve node:path"}},{"file":"node:path","fn":"isPathSeparator","id":"1","ix":"0","pos":"1794","caller":{"file":"node:path","fn":"resolve","id":"1","ix":"-1","pos":"4875","key":"resolve node:path"}},{"file":"node:path","fn":"isPathSeparator","id":"1","ix":"0","pos":"1794","caller":{"file":"node:path","fn":"resolve","id":"1","ix":"-1","pos":"4875","key":"resolve node:path"}},{"file":"node:path","fn":"isPathSeparator","id":"4","ix":"0","pos":"1794","caller":{"file":"node:path","fn":"dirname","id":"4","ix":"-1","pos":"21280","key":"dirname node:path"}},{"file":"node:path","fn":"isPathSeparator","id":"4","ix":"0","pos":"1794","caller":{"file":"node:path","fn":"dirname","id":"4","ix":"-1","pos":"21280","key":"dirname node:path"}},{"file":"node:path","fn":"isPathSeparator","id":"4","ix":"0","pos":"1794","caller":{"file":"node:path","fn":"dirname","id":"4","ix":"-1","pos":"21280","key":"dirname node:path"}},{"file":"node:path","fn":"isPathSeparator","id":"8","ix":"0","pos":"1794","caller":{"file":"node:path","fn":"resolve","id":"8","ix":"-1","pos":"4875","key":"resolve node:path"}},{"file":"node:path","fn":"isPathSeparator","id":"8","ix":"0","pos":"1794","caller":{"file":"node:path","fn":"resolve","id":"8","ix":"-1","pos":"4875","key":"resolve node:path"}},{"file":"node:path","fn":"isPathSeparator","id":"8","ix":"0","pos":"1794","caller":{"file":"node:path","fn":"resolve","id":"8","ix":"-1","pos":"4875","key":"resolve node:path"}},{"file":"node:path","fn":"isPathSeparator","id":"8","ix":"0","pos":"1794","caller":{"file":"node:path","fn":"resolve","id":"8","ix":"-1","pos":"4875","key":"resolve node:path"}},{"file":"node:path","fn":"isPathSeparator","id":"9","ix":"0","pos":"1794","caller":{"file":"node:path","fn":"basename","id":"9","ix":"-1","pos":"24016","key":"basename node:path"}},{"file":"node:path","fn":"isPathSeparator","id":"18","ix":"4","pos":"1794","caller":{"file":"node:internal/modules/cjs/loader","fn":"Module._findPath","id":"18","ix":"-1","pos":"14820","key":"Module._findPath node:internal/modules/cjs/loader"}},{"file":"node:path","fn":"isPathSeparator","id":"19","ix":"2","pos":"1794","caller":{"file":"node:internal/modules/cjs/loader","fn":"Module._compile","id":"19","ix":"-1","pos":"33952","key":"Module._compile node:internal/modules/cjs/loader"}},{"file":"node:path","fn":"isPathSeparator","id":"19","ix":"2","pos":"1794","caller":{"file":"node:internal/modules/cjs/loader","fn":"Module._compile","id":"19","ix":"-1","pos":"33952","key":"Module._compile node:internal/modules/cjs/loader"}},{"file":"node:path","fn":"isPathSeparator","id":"19","ix":"2","pos":"1794","caller":{"file":"node:internal/modules/cjs/loader","fn":"Module._compile","id":"19","ix":"-1","pos":"33952","key":"Module._compile node:internal/modules/cjs/loader"}},{"file":"node:path","fn":"isPathSeparator","id":"21","ix":"3","pos":"1794","caller":{"file":"node:internal/modules/cjs/loader","fn":"Module._resolveLookupPaths","id":"21","ix":"-1","pos":"20630","key":"Module._resolveLookupPaths node:internal/modules/cjs/loader"}},{"file":"node:path","fn":"isPathSeparator","id":"21","ix":"3","pos":"1794","caller":{"file":"node:internal/modules/cjs/loader","fn":"Module._resolveLookupPaths","id":"21","ix":"-1","pos":"20630","key":"Module._resolveLookupPaths node:internal/modules/cjs/loader"}},{"file":"node:path","fn":"isPathSeparator","id":"21","ix":"3","pos":"1794","caller":{"file":"node:internal/modules/cjs/loader","fn":"Module._resolveLookupPaths","id":"21","ix":"-1","pos":"20630","key":"Module._resolveLookupPaths node:internal/modules/cjs/loader"}}],"isWindowsDeviceRoot node:path":[{"file":"node:path","fn":"isWindowsDeviceRoot","id":"1","ix":"1","pos":"1991","caller":{"file":"node:path","fn":"resolve","id":"1","ix":"-1","pos":"4875","key":"resolve node:path"}},{"file":"node:path","fn":"isWindowsDeviceRoot","id":"4","ix":"1","pos":"1991","caller":{"file":"node:path","fn":"dirname","id":"4","ix":"-1","pos":"21280","key":"dirname node:path"}},{"file":"node:path","fn":"isWindowsDeviceRoot","id":"5","ix":"0","pos":"1991","caller":{"file":"node:path","fn":"toNamespacedPath","id":"5","ix":"-1","pos":"20086","key":"toNamespacedPath node:path"}},{"file":"node:path","fn":"isWindowsDeviceRoot","id":"8","ix":"1","pos":"1991","caller":{"file":"node:path","fn":"resolve","id":"8","ix":"-1","pos":"4875","key":"resolve node:path"}},{"file":"node:path","fn":"isWindowsDeviceRoot","id":"9","ix":"1","pos":"1991","caller":{"file":"node:path","fn":"basename","id":"9","ix":"-1","pos":"24016","key":"basename node:path"}},{"file":"node:path","fn":"isWindowsDeviceRoot","id":"13","ix":"1","pos":"1991","caller":{"file":"node:internal/modules/cjs/loader","fn":"stat","id":"13","ix":"-1","pos":"4777","key":"stat node:internal/modules/cjs/loader"}},{"file":"node:path","fn":"isWindowsDeviceRoot","id":"18","ix":"2","pos":"1991","caller":{"file":"node:internal/modules/cjs/loader","fn":"Module._findPath","id":"18","ix":"-1","pos":"14820","key":"Module._findPath node:internal/modules/cjs/loader"}},{"file":"node:path","fn":"isWindowsDeviceRoot","id":"18","ix":"2","pos":"1991","caller":{"file":"node:internal/modules/cjs/loader","fn":"Module._findPath","id":"18","ix":"-1","pos":"14820","key":"Module._findPath node:internal/modules/cjs/loader"}},{"file":"node:path","fn":"isWindowsDeviceRoot","id":"19","ix":"5","pos":"1991","caller":{"file":"node:internal/modules/cjs/loader","fn":"Module._compile","id":"19","ix":"-1","pos":"33952","key":"Module._compile node:internal/modules/cjs/loader"}},{"file":"node:path","fn":"isWindowsDeviceRoot","id":"21","ix":"4","pos":"1991","caller":{"file":"node:internal/modules/cjs/loader","fn":"Module._resolveLookupPaths","id":"21","ix":"-1","pos":"20630","key":"Module._resolveLookupPaths node:internal/modules/cjs/loader"}}],"validateString node:internal/validators":[{"file":"node:internal/validators","fn":"validateString","id":"1","ix":"2","pos":"3534","caller":{"file":"node:path","fn":"resolve","id":"1","ix":"-1","pos":"4875","key":"resolve node:path"}},{"file":"node:internal/validators","fn":"validateString","id":"4","ix":"2","pos":"3534","caller":{"file":"node:path","fn":"dirname","id":"4","ix":"-1","pos":"21280","key":"dirname node:path"}},{"file":"node:internal/validators","fn":"validateString","id":"8","ix":"2","pos":"3534","caller":{"file":"node:path","fn":"resolve","id":"8","ix":"-1","pos":"4875","key":"resolve node:path"}},{"file":"node:internal/validators","fn":"validateString","id":"9","ix":"2","pos":"3534","caller":{"file":"node:path","fn":"basename","id":"9","ix":"-1","pos":"24016","key":"basename node:path"}},{"file":"node:internal/validators","fn":"validateString","id":"17","ix":"8","pos":"3534","caller":{"file":"node:vm","fn":"compileFunction","id":"17","ix":"-1","pos":"9869","key":"compileFunction node:vm"}},{"file":"node:internal/validators","fn":"validateString","id":"17","ix":"8","pos":"3534","caller":{"file":"node:vm","fn":"compileFunction","id":"17","ix":"-1","pos":"9869","key":"compileFunction node:vm"}},{"file":"node:internal/validators","fn":"validateString","id":"18","ix":"5","pos":"3534","caller":{"file":"node:internal/modules/cjs/loader","fn":"Module._findPath","id":"18","ix":"-1","pos":"14820","key":"Module._findPath node:internal/modules/cjs/loader"}},{"file":"node:internal/validators","fn":"validateString","id":"19","ix":"6","pos":"3534","caller":{"file":"node:internal/modules/cjs/loader","fn":"Module._compile","id":"19","ix":"-1","pos":"33952","key":"Module._compile node:internal/modules/cjs/loader"}},{"file":"node:internal/validators","fn":"validateString","id":"21","ix":"5","pos":"3534","caller":{"file":"node:internal/modules/cjs/loader","fn":"Module._resolveLookupPaths","id":"21","ix":"-1","pos":"20630","key":"Module._resolveLookupPaths node:internal/modules/cjs/loader"}},{"file":"node:internal/validators","fn":"validateString","id":"26","ix":"0","pos":"3534","caller":{"file":"node:vm","fn":"(anonymous)","id":"26","ix":"-1","pos":"10064","key":"(anonymous) node:vm"}}],"normalizeString node:path":[{"file":"node:path","fn":"normalizeString","id":"1","ix":"3","pos":"2226","caller":{"file":"node:path","fn":"resolve","id":"1","ix":"-1","pos":"4875","key":"resolve node:path"}},{"file":"node:path","fn":"normalizeString","id":"8","ix":"3","pos":"2226","caller":{"file":"node:path","fn":"resolve","id":"8","ix":"-1","pos":"4875","key":"resolve node:path"}}],"getOwn node:internal/bootstrap/loaders":[{"file":"node:internal/bootstrap/loaders","fn":"getOwn","id":"7","ix":"0","pos":"5677","caller":{"file":"node:internal/bootstrap/loaders","fn":"syncExports","id":"7","ix":"-1","pos":"9454","key":"syncExports node:internal/bootstrap/loaders"}}],"readPackage node:internal/modules/cjs/loader":[{"file":"node:internal/modules/cjs/loader","fn":"readPackage","id":"10","ix":"0","pos":"8391","caller":{"file":"node:internal/modules/cjs/loader","fn":"readPackageScope","id":"10","ix":"-1","pos":"9239","key":"readPackageScope node:internal/modules/cjs/loader"}},{"file":"node:internal/modules/cjs/loader","fn":"readPackage","id":"14","ix":"0","pos":"8391","caller":{"file":"node:internal/modules/cjs/loader","fn":"readPackageScope","id":"14","ix":"-1","pos":"9239","key":"readPackageScope node:internal/modules/cjs/loader"}}],"noop node:internal/util/debuglog":[{"file":"node:internal/util/debuglog","fn":"noop","id":"11","ix":"0","pos":"1465","caller":{"file":"node:internal/modules/cjs/loader","fn":"Module._load","id":"11","ix":"-1","pos":"23964","key":"Module._load node:internal/modules/cjs/loader"}},{"file":"node:internal/util/debuglog","fn":"noop","id":"11","ix":"0","pos":"1465","caller":{"file":"node:internal/modules/cjs/loader","fn":"Module._load","id":"11","ix":"-1","pos":"23964","key":"Module._load node:internal/modules/cjs/loader"}},{"file":"node:internal/util/debuglog","fn":"noop","id":"21","ix":"0","pos":"1465","caller":{"file":"node:internal/modules/cjs/loader","fn":"Module._resolveLookupPaths","id":"21","ix":"-1","pos":"20630","key":"Module._resolveLookupPaths node:internal/modules/cjs/loader"}},{"file":"node:internal/util/debuglog","fn":"noop","id":"21","ix":"0","pos":"1465","caller":{"file":"node:internal/modules/cjs/loader","fn":"Module._resolveLookupPaths","id":"21","ix":"-1","pos":"20630","key":"Module._resolveLookupPaths node:internal/modules/cjs/loader"}}],"loadNativeModule node:internal/modules/cjs/helpers":[{"file":"node:internal/modules/cjs/helpers","fn":"loadNativeModule","id":"11","ix":"1","pos":"1194","caller":{"file":"node:internal/modules/cjs/loader","fn":"Module._load","id":"11","ix":"-1","pos":"23964","key":"Module._load node:internal/modules/cjs/loader"}}],"Module.load node:internal/modules/cjs/loader":[{"file":"node:internal/modules/cjs/loader","fn":"Module.load","id":"11","ix":"2","pos":"31233","caller":{"file":"node:internal/modules/cjs/loader","fn":"Module._load","id":"11","ix":"-1","pos":"23964","key":"Module._load node:internal/modules/cjs/loader"}}],"assert node:internal/assert":[{"file":"node:internal/assert","fn":"assert","id":"11","ix":"3","pos":"182","caller":{"file":"node:internal/modules/cjs/loader","fn":"Module._load","id":"11","ix":"-1","pos":"23964","key":"Module._load node:internal/modules/cjs/loader"}}],"Module node:internal/modules/cjs/loader":[{"file":"node:internal/modules/cjs/loader","fn":"Module","id":"11","ix":"4","pos":"5455","caller":{"file":"node:internal/modules/cjs/loader","fn":"Module._load","id":"11","ix":"-1","pos":"23964","key":"Module._load node:internal/modules/cjs/loader"}}],"updateChildren node:internal/modules/cjs/loader":[{"file":"node:internal/modules/cjs/loader","fn":"updateChildren","id":"11","ix":"5","pos":"5213","caller":{"file":"node:internal/modules/cjs/loader","fn":"Module._load","id":"11","ix":"-1","pos":"23964","key":"Module._load node:internal/modules/cjs/loader"}},{"file":"node:internal/modules/cjs/loader","fn":"updateChildren","id":"11","ix":"5","pos":"5213","caller":{"file":"node:internal/modules/cjs/loader","fn":"Module._load","id":"11","ix":"-1","pos":"23964","key":"Module._load node:internal/modules/cjs/loader"}},{"file":"node:internal/modules/cjs/loader","fn":"updateChildren","id":"11","ix":"5","pos":"5213","caller":{"file":"node:internal/modules/cjs/loader","fn":"Module._load","id":"11","ix":"-1","pos":"23964","key":"Module._load node:internal/modules/cjs/loader"}}],"findLongestRegisteredExtension node:internal/modules/cjs/loader":[{"file":"node:internal/modules/cjs/loader","fn":"findLongestRegisteredExtension","id":"11","ix":"6","pos":"12225","caller":{"file":"node:internal/modules/cjs/loader","fn":"Module._load","id":"11","ix":"-1","pos":"23964","key":"Module._load node:internal/modules/cjs/loader"}}],"Module._nodeModulePaths node:internal/modules/cjs/loader":[{"file":"node:internal/modules/cjs/loader","fn":"Module._nodeModulePaths","id":"11","ix":"7","pos":"17765","caller":{"file":"node:internal/modules/cjs/loader","fn":"Module._load","id":"11","ix":"-1","pos":"23964","key":"Module._load node:internal/modules/cjs/loader"}}],"toNamespacedPath node:path":[{"file":"node:path","fn":"toNamespacedPath","id":"13","ix":"0","pos":"20086","caller":{"file":"node:internal/modules/cjs/loader","fn":"stat","id":"13","ix":"-1","pos":"4777","key":"stat node:internal/modules/cjs/loader"}},{"file":"node:path","fn":"toNamespacedPath","id":"18","ix":"1","pos":"20086","caller":{"file":"node:internal/modules/cjs/loader","fn":"Module._findPath","id":"18","ix":"-1","pos":"14820","key":"Module._findPath node:internal/modules/cjs/loader"}}],"isUint32 node:internal/validators":[{"file":"node:internal/validators","fn":"isUint32","id":"16","ix":"0","pos":"835","caller":{"file":"node:fs","fn":"readFileSync","id":"16","ix":"-1","pos":"11796","key":"readFileSync node:fs"}},{"file":"node:internal/validators","fn":"isUint32","id":"17","ix":"7","pos":"835","caller":{"file":"node:vm","fn":"compileFunction","id":"17","ix":"-1","pos":"9869","key":"compileFunction node:vm"}},{"file":"node:internal/validators","fn":"isUint32","id":"17","ix":"7","pos":"835","caller":{"file":"node:vm","fn":"compileFunction","id":"17","ix":"-1","pos":"9869","key":"compileFunction node:vm"}}],"tryReadSync node:fs":[{"file":"node:fs","fn":"tryReadSync","id":"16","ix":"1","pos":"11295","caller":{"file":"node:fs","fn":"readFileSync","id":"16","ix":"-1","pos":"11796","key":"readFileSync node:fs"}}],"tryCreateBuffer node:fs":[{"file":"node:fs","fn":"tryCreateBuffer","id":"16","ix":"2","pos":"10971","caller":{"file":"node:fs","fn":"readFileSync","id":"16","ix":"-1","pos":"11796","key":"readFileSync node:fs"}}],"allocUnsafe node:buffer":[{"file":"node:buffer","fn":"allocUnsafe","id":"16","ix":"3","pos":"11242","caller":{"file":"node:fs","fn":"readFileSync","id":"16","ix":"-1","pos":"11796","key":"readFileSync node:fs"}}],"isFileType node:fs":[{"file":"node:fs","fn":"isFileType","id":"16","ix":"4","pos":"5489","caller":{"file":"node:fs","fn":"readFileSync","id":"16","ix":"-1","pos":"11796","key":"readFileSync node:fs"}}],"tryStatSync node:fs":[{"file":"node:fs","fn":"tryStatSync","id":"16","ix":"5","pos":"10725","caller":{"file":"node:fs","fn":"readFileSync","id":"16","ix":"-1","pos":"11796","key":"readFileSync node:fs"}}],"openSync node:fs":[{"file":"node:fs","fn":"openSync","id":"16","ix":"6","pos":"14993","caller":{"file":"node:fs","fn":"readFileSync","id":"16","ix":"-1","pos":"11796","key":"readFileSync node:fs"}}],"getOptions node:internal/fs/utils":[{"file":"node:internal/fs/utils","fn":"getOptions","id":"16","ix":"7","pos":"7531","caller":{"file":"node:fs","fn":"readFileSync","id":"16","ix":"-1","pos":"11796","key":"readFileSync node:fs"}}],"handleErrorFromBinding node:internal/fs/utils":[{"file":"node:internal/fs/utils","fn":"handleErrorFromBinding","id":"16","ix":"8","pos":"8269","caller":{"file":"node:fs","fn":"readFileSync","id":"16","ix":"-1","pos":"11796","key":"readFileSync node:fs"}},{"file":"node:internal/fs/utils","fn":"handleErrorFromBinding","id":"20","ix":"0","pos":"8269","caller":{"file":"node:fs","fn":"readSync","id":"20","ix":"-1","pos":"17803","key":"readSync node:fs"}}],"parseFileMode node:internal/validators":[{"file":"node:internal/validators","fn":"parseFileMode","id":"16","ix":"9","pos":"1545","caller":{"file":"node:fs","fn":"readFileSync","id":"16","ix":"-1","pos":"11796","key":"readFileSync node:fs"}}],"toPathIfFileURL node:internal/url":[{"file":"node:internal/url","fn":"toPathIfFileURL","id":"16","ix":"11","pos":"42956","caller":{"file":"node:fs","fn":"readFileSync","id":"16","ix":"-1","pos":"11796","key":"readFileSync node:fs"}}],"isURLInstance node:internal/url":[{"file":"node:internal/url","fn":"isURLInstance","id":"16","ix":"12","pos":"42829","caller":{"file":"node:fs","fn":"readFileSync","id":"16","ix":"-1","pos":"11796","key":"readFileSync node:fs"}}],"get href node:internal/url":[{"file":"node:internal/url","fn":"get href","id":"16","ix":"13","pos":"20841","caller":{"file":"node:fs","fn":"readFileSync","id":"16","ix":"-1","pos":"11796","key":"readFileSync node:fs"}}],"assertEncoding node:internal/fs/utils":[{"file":"node:internal/fs/utils","fn":"assertEncoding","id":"16","ix":"14","pos":"3677","caller":{"file":"node:fs","fn":"readFileSync","id":"16","ix":"-1","pos":"11796","key":"readFileSync node:fs"}}],"importModuleDynamicallyWrap node:internal/vm/module":[{"file":"node:internal/vm/module","fn":"importModuleDynamicallyWrap","id":"17","ix":"0","pos":"12139","caller":{"file":"node:vm","fn":"compileFunction","id":"17","ix":"-1","pos":"9869","key":"compileFunction node:vm"}}],"internalBinding node:internal/bootstrap/loaders":[{"file":"node:internal/bootstrap/loaders","fn":"internalBinding","id":"17","ix":"1","pos":"5278","caller":{"file":"node:vm","fn":"compileFunction","id":"17","ix":"-1","pos":"9869","key":"compileFunction node:vm"}}],"nativeModuleRequire node:internal/bootstrap/loaders":[{"file":"node:internal/bootstrap/loaders","fn":"nativeModuleRequire","id":"17","ix":"2","pos":"10647","caller":{"file":"node:vm","fn":"compileFunction","id":"17","ix":"-1","pos":"9869","key":"compileFunction node:vm"}}],"validateBoolean node:internal/validators":[{"file":"node:internal/validators","fn":"validateBoolean","id":"17","ix":"5","pos":"4199","caller":{"file":"node:vm","fn":"compileFunction","id":"17","ix":"-1","pos":"9869","key":"compileFunction node:vm"}}],"stat node:internal/modules/cjs/loader":[{"file":"node:internal/modules/cjs/loader","fn":"stat","id":"18","ix":"0","pos":"4777","caller":{"file":"node:internal/modules/cjs/loader","fn":"Module._findPath","id":"18","ix":"-1","pos":"14820","key":"Module._findPath node:internal/modules/cjs/loader"}}],"isAbsolute node:path":[{"file":"node:path","fn":"isAbsolute","id":"18","ix":"3","pos":"13104","caller":{"file":"node:internal/modules/cjs/loader","fn":"Module._findPath","id":"18","ix":"-1","pos":"14820","key":"Module._findPath node:internal/modules/cjs/loader"}}],"resolveExports node:internal/modules/cjs/loader":[{"file":"node:internal/modules/cjs/loader","fn":"resolveExports","id":"18","ix":"6","pos":"14039","caller":{"file":"node:internal/modules/cjs/loader","fn":"Module._findPath","id":"18","ix":"-1","pos":"14820","key":"Module._findPath node:internal/modules/cjs/loader"}}],"tryExtensions node:internal/modules/cjs/loader":[{"file":"node:internal/modules/cjs/loader","fn":"tryExtensions","id":"18","ix":"7","pos":"11900","caller":{"file":"node:internal/modules/cjs/loader","fn":"Module._findPath","id":"18","ix":"-1","pos":"14820","key":"Module._findPath node:internal/modules/cjs/loader"}}],"tryFile node:internal/modules/cjs/loader":[{"file":"node:internal/modules/cjs/loader","fn":"tryFile","id":"18","ix":"8","pos":"11460","caller":{"file":"node:internal/modules/cjs/loader","fn":"Module._findPath","id":"18","ix":"-1","pos":"14820","key":"Module._findPath node:internal/modules/cjs/loader"}}],"toRealPath node:internal/modules/cjs/loader":[{"file":"node:internal/modules/cjs/loader","fn":"toRealPath","id":"18","ix":"9","pos":"11684","caller":{"file":"node:internal/modules/cjs/loader","fn":"Module._findPath","id":"18","ix":"-1","pos":"14820","key":"Module._findPath node:internal/modules/cjs/loader"}}],"makeRequireFunction node:internal/modules/cjs/helpers":[{"file":"node:internal/modules/cjs/helpers","fn":"makeRequireFunction","id":"19","ix":"0","pos":"1765","caller":{"file":"node:internal/modules/cjs/loader","fn":"Module._compile","id":"19","ix":"-1","pos":"33952","key":"Module._compile node:internal/modules/cjs/loader"}}],"dirname node:path":[{"file":"node:path","fn":"dirname","id":"19","ix":"1","pos":"21280","caller":{"file":"node:internal/modules/cjs/loader","fn":"Module._compile","id":"19","ix":"-1","pos":"33952","key":"Module._compile node:internal/modules/cjs/loader"}},{"file":"node:path","fn":"dirname","id":"21","ix":"2","pos":"21280","caller":{"file":"node:internal/modules/cjs/loader","fn":"Module._resolveLookupPaths","id":"21","ix":"-1","pos":"20630","key":"Module._resolveLookupPaths node:internal/modules/cjs/loader"}}],"getOptionValue node:internal/options":[{"file":"node:internal/options","fn":"getOptionValue","id":"19","ix":"3","pos":"940","caller":{"file":"node:internal/modules/cjs/loader","fn":"Module._compile","id":"19","ix":"-1","pos":"33952","key":"Module._compile node:internal/modules/cjs/loader"}}],"getCLIOptionsFromBinding node:internal/options":[{"file":"node:internal/options","fn":"getCLIOptionsFromBinding","id":"19","ix":"4","pos":"514","caller":{"file":"node:internal/modules/cjs/loader","fn":"Module._compile","id":"19","ix":"-1","pos":"33952","key":"Module._compile node:internal/modules/cjs/loader"}}],"isInt32 node:internal/validators":[{"file":"node:internal/validators","fn":"isInt32","id":"20","ix":"7","pos":"769","caller":{"file":"node:fs","fn":"readSync","id":"20","ix":"-1","pos":"17803","key":"readSync node:fs"}},{"file":"node:internal/validators","fn":"isInt32","id":"25","ix":"0","pos":"769","caller":{"file":"node:internal/validators","fn":"(anonymous)","id":"25","ix":"-1","pos":"2338","key":"(anonymous) node:internal/validators"}}],"canBeRequiredByUsers node:internal/bootstrap/loaders":[{"file":"node:internal/bootstrap/loaders","fn":"canBeRequiredByUsers","id":"21","ix":"1","pos":"7593","caller":{"file":"node:internal/modules/cjs/loader","fn":"Module._resolveLookupPaths","id":"21","ix":"-1","pos":"20630","key":"Module._resolveLookupPaths node:internal/modules/cjs/loader"}}],"unsigned32 D:\\FRANCO\\Curso programacion\\Practica\\router\\node_modules\\@faker-js\\faker\\dist\\cjs\\modules\\mersenne\\twister.js":[{"file":"D:\\FRANCO\\Curso programacion\\Practica\\router\\node_modules\\@faker-js\\faker\\dist\\cjs\\modules\\mersenne\\twister.js","fn":"unsigned32","id":"24","ix":"0","pos":"681","caller":{"file":"D:\\FRANCO\\Curso programacion\\Practica\\router\\node_modules\\@faker-js\\faker\\dist\\cjs\\modules\\mersenne\\twister.js","fn":"addition32","id":"24","ix":"-1","pos":"823","key":"addition32 D:\\FRANCO\\Curso programacion\\Practica\\router\\node_modules\\@faker-js\\faker\\dist\\cjs\\modules\\mersenne\\twister.js"}},{"file":"D:\\FRANCO\\Curso programacion\\Practica\\router\\node_modules\\@faker-js\\faker\\dist\\cjs\\modules\\mersenne\\twister.js","fn":"unsigned32","id":"22","ix":"0","pos":"681","caller":{"file":"D:\\FRANCO\\Curso programacion\\Practica\\router\\node_modules\\@faker-js\\faker\\dist\\cjs\\modules\\mersenne\\twister.js","fn":"multiplication32","id":"22","ix":"-1","pos":"884","key":"multiplication32 D:\\FRANCO\\Curso programacion\\Practica\\router\\node_modules\\@faker-js\\faker\\dist\\cjs\\modules\\mersenne\\twister.js"}},{"file":"D:\\FRANCO\\Curso programacion\\Practica\\router\\node_modules\\@faker-js\\faker\\dist\\cjs\\modules\\mersenne\\twister.js","fn":"unsigned32","id":"22","ix":"0","pos":"681","caller":{"file":"D:\\FRANCO\\Curso programacion\\Practica\\router\\node_modules\\@faker-js\\faker\\dist\\cjs\\modules\\mersenne\\twister.js","fn":"multiplication32","id":"22","ix":"-1","pos":"884","key":"multiplication32 D:\\FRANCO\\Curso programacion\\Practica\\router\\node_modules\\@faker-js\\faker\\dist\\cjs\\modules\\mersenne\\twister.js"}}],"addition32 D:\\FRANCO\\Curso programacion\\Practica\\router\\node_modules\\@faker-js\\faker\\dist\\cjs\\modules\\mersenne\\twister.js":[{"file":"D:\\FRANCO\\Curso programacion\\Practica\\router\\node_modules\\@faker-js\\faker\\dist\\cjs\\modules\\mersenne\\twister.js","fn":"addition32","id":"22","ix":"1","pos":"823","caller":{"file":"D:\\FRANCO\\Curso programacion\\Practica\\router\\node_modules\\@faker-js\\faker\\dist\\cjs\\modules\\mersenne\\twister.js","fn":"multiplication32","id":"22","ix":"-1","pos":"884","key":"multiplication32 D:\\FRANCO\\Curso programacion\\Practica\\router\\node_modules\\@faker-js\\faker\\dist\\cjs\\modules\\mersenne\\twister.js"}}]}}